AILungMeasure/__init__.py
AILungMeasure/cv_functions.py
AILungMeasure/main_function.py
AILungMeasure/model_functions.py
AILungMeasure/segment_functions.py
AILungMeasure/utils.py
AILungMeasure-0.2.3.dist-info/METADATA
AILungMeasure-0.2.3.dist-info/WHEEL
AILungMeasure-0.2.3.dist-info/top_level.txt
AILungMeasure-0.2.3.dist-info/RECORD
