Metadata-Version: 2.1
Name: AILungMeasure
Version: 0.2.3
Summary: Automated lung size measurements using deep learning and computer vision on portable chest radiographs.
Home-page: https://doi.org/10.1016/j.ajt.2024.08.015
Author: Mostafa Ismail
Author-email: mostafa.ismail.k@gmail.com
License: Creative Commons Attribution-NonCommercial-ShareAlike 4.0 International
Project-URL: DOI, https://doi.org/10.1016/j.ajt.2024.08.015
Classifier: Programming Language :: Python :: 3
Classifier: License :: Other/Proprietary License
Classifier: Operating System :: OS Independent
Requires-Python: >=3.6
Requires-Dist: torch
Requires-Dist: Pillow
Requires-Dist: torchvision
Requires-Dist: matplotlib
Requires-Dist: opencv-python
Requires-Dist: numpy
Requires-Dist: imutils
Requires-Dist: gdown
Requires-Dist: pydicom
